nba_python/__init__.py
tests/__init__.py
NBA_Python-0.0.1.dist-info/LICENSE
NBA_Python-0.0.1.dist-info/METADATA
NBA_Python-0.0.1.dist-info/WHEEL
NBA_Python-0.0.1.dist-info/top_level.txt
NBA_Python-0.0.1.dist-info/RECORD
